vtracerpy-0.1.3.dist-info/METADATA
vtracerpy-0.1.3.dist-info/WHEEL
vtracerpy-0.1.3.dist-info/license_files/LICENSE
vtracerpy/__init__.py
vtracerpy/vtracerpy.pypy310-pp73-s390x-linux-gnu.so
vtracerpy-0.1.3.dist-info/RECORD
