Metadata-Version: 2.1
Name: vtracerpy
Version: 0.1.3
Classifier: Programming Language :: Rust
Classifier: Programming Language :: Python :: Implementation :: CPython
Classifier: Programming Language :: Python :: Implementation :: PyPy
License-File: LICENSE
Summary: Python binding for vtracer. image to svg.
Requires-Python: >=3.7
